api_tester_mcp/__init__.py
api_tester_mcp/__main__.py
api_tester_mcp/code_generators.py
api_tester_mcp/models.py
api_tester_mcp/parsers.py
api_tester_mcp/reports.py
api_tester_mcp/server.py
api_tester_mcp/test_execution.py
api_tester_mcp/utils.py
api_tester_mcp-1.5.0.dist-info/LICENSE
api_tester_mcp-1.5.0.dist-info/METADATA
api_tester_mcp-1.5.0.dist-info/WHEEL
api_tester_mcp-1.5.0.dist-info/entry_points.txt
api_tester_mcp-1.5.0.dist-info/top_level.txt
api_tester_mcp-1.5.0.dist-info/RECORD
