Metadata-Version: 2.1
Name: api-tester-mcp
Version: 1.5.0
Summary: Multi-language MCP server for API testing with TypeScript/Playwright, JavaScript/Jest, Python/pytest support
Home-page: https://github.com/kirti676/api_tester_mcp
Author: API Tester MCP
Author-email: API Tester MCP <api-tester@example.com>
License: MIT
Project-URL: Repository, https://github.com/kirti676/api_tester_mcp.git
Project-URL: Issues, https://github.com/kirti676/api_tester_mcp/issues
Project-URL: Changelog, https://github.com/kirti676/api_tester_mcp/blob/main/CHANGELOG.md
Classifier: Development Status :: 5 - Production/Stable
Classifier: Intended Audience :: Developers
Classifier: Operating System :: OS Independent
Classifier: Programming Language :: Python :: 3
Classifier: Programming Language :: Python :: 3.8
Classifier: Programming Language :: Python :: 3.9
Classifier: Programming Language :: Python :: 3.10
Classifier: Programming Language :: Python :: 3.11
Classifier: Programming Language :: Python :: 3.12
Classifier: Topic :: Software Development :: Testing
Classifier: Topic :: Internet :: WWW/HTTP
Classifier: Topic :: Software Development :: Quality Assurance
Requires-Python: >=3.8
License-File: LICENSE
Requires-Dist: fastmcp>=0.2.0
Requires-Dist: pydantic>=2.0.0
Requires-Dist: jsonschema>=4.0.0
Requires-Dist: pyyaml>=6.0
Requires-Dist: jinja2>=3.1.0
Requires-Dist: aiohttp>=3.8.0
Requires-Dist: faker>=19.0.0
Provides-Extra: dev
Requires-Dist: pytest>=7.0.0; extra == "dev"
Requires-Dist: pytest-asyncio>=0.21.0; extra == "dev"
Requires-Dist: black>=23.0.0; extra == "dev"
Requires-Dist: isort>=5.12.0; extra == "dev"
Requires-Dist: mypy>=1.5.0; extra == "dev"
